chuk_mcp_virtual_fs/__init__.py
chuk_mcp_virtual_fs/main.py
chuk_mcp_virtual_fs/models.py
chuk_mcp_virtual_fs/tools.py
chuk_mcp_virtual_fs-0.1.0.dist-info/licenses/LICENSE.md
chuk_mcp_virtual_fs-0.1.0.dist-info/METADATA
chuk_mcp_virtual_fs-0.1.0.dist-info/WHEEL
chuk_mcp_virtual_fs-0.1.0.dist-info/entry_points.txt
chuk_mcp_virtual_fs-0.1.0.dist-info/top_level.txt
chuk_mcp_virtual_fs-0.1.0.dist-info/RECORD
