Metadata-Version: 2.4
Name: chuk-mcp-virtual-fs
Version: 0.1.0
Summary: MCP Virtual Filesystem
Project-URL: Homepage, https://github.com/chrishayuk/chuk-mcp-s3-bucket-manager
Project-URL: Bug Tracker, https://github.com/chrishayuk/chuk-mcp-s3-bucket-manager/issues
Requires-Python: >=3.11
License-File: LICENSE.md
Requires-Dist: boto3>=1.37.31
Requires-Dist: chuk-mcp-runtime>=0.1.1
Requires-Dist: chuk-virtual-fs>=0.1.10
Requires-Dist: mcp>=1.6.0
Requires-Dist: pydantic>=2.11.2
Requires-Dist: pyyaml>=6.0.2
Dynamic: license-file
